dataclass_extensions/__init__.py
dataclass_extensions/decode.py
dataclass_extensions/encode.py
dataclass_extensions/py.typed
dataclass_extensions/registrable.py
dataclass_extensions/types.py
dataclass_extensions/utils.py
dataclass_extensions/version.py
dataclass_extensions-0.2.3.dist-info/licenses/LICENSE
dataclass_extensions-0.2.3.dist-info/METADATA
dataclass_extensions-0.2.3.dist-info/WHEEL
dataclass_extensions-0.2.3.dist-info/top_level.txt
dataclass_extensions-0.2.3.dist-info/RECORD
