Metadata-Version: 2.4
Name: dataclass-extensions
Version: 0.2.3
Summary: Additional functionality for Python dataclasses
Author-email: Pete Walsh <epwalsh10@gmail.com>
License:                                  Apache License
Project-URL: Homepage, https://github.com/epwalsh/dataclass-extensions
Project-URL: Changelog, https://github.com/epwalsh/dataclass-extensions/blob/main/CHANGELOG.md
Requires-Python: >=3.10
License-File: LICENSE
Provides-Extra: dev
Requires-Dist: ruff; extra == "dev"
Requires-Dist: mypy; extra == "dev"
Requires-Dist: black<24.0,>=23.1; extra == "dev"
Requires-Dist: isort<5.14,>=5.12; extra == "dev"
Requires-Dist: pytest; extra == "dev"
Requires-Dist: twine>=1.11.0; extra == "dev"
Requires-Dist: setuptools; extra == "dev"
Requires-Dist: wheel; extra == "dev"
Requires-Dist: build; extra == "dev"
Provides-Extra: all
Requires-Dist: dataclass-extensions[dev]; extra == "all"
Dynamic: license-file
